replitdev/.vscode/settings.json
replitdev/__init__.py
replitdev/audio/Makefile
replitdev/audio/__init__.py
replitdev/audio/test.py
replitdev/audio/types.py
replitdev/database/__init__.py
replitdev/database/database.py
replitdev/database/jsonkey.py
replitdev/termutils.py
replitdev/users.py
replitdev/web/__init__.py
replitdev/web/app.py
replitdev/web/files.py
replitdev/web/html.py
replitdev/web/utils.py
replitdev-2.5.22.dist-info/LICENSE
replitdev-2.5.22.dist-info/WHEEL
replitdev-2.5.22.dist-info/METADATA
replitdev-2.5.22.dist-info/RECORD
