Metadata-Version: 2.1
Name: replitdev
Version: 2.5.22
Summary: A library for interacting with features of repl.it
Home-page: https://github.com/replit/replit-py
License: MIT
Author: mat
Author-email: pypi@matdoes.dev
Requires-Python: >=3.8,<4.0
Classifier: License :: OSI Approved :: MIT License
Classifier: Programming Language :: Python :: 3
Classifier: Programming Language :: Python :: 3.8
Classifier: Programming Language :: Python :: 3.9
Requires-Dist: aiohttp (>=3.6.2,<4.0.0)
Requires-Dist: flask (>=1.1.2,<2.0.0)
Requires-Dist: requests-html (>=0.10.0,<0.11.0)
Requires-Dist: typing_extensions (>=3.7.4,<4.0.0)
Requires-Dist: werkzeug (>=1.0.1,<2.0.0)
Project-URL: Documentation, https://replit-python-docs.scoder12.repl.co
Project-URL: Repository, https://github.com/replit/replit-py
